pyburg/Tree.py
pyburg/__init__.py
pyburg/brg2py.py
pyburg/postfix.py
pyburg/pyburg.py
pyburg/strbuf.py
pyburg_pkg_peresan-1.4.1.dist-info/LICENSE
pyburg_pkg_peresan-1.4.1.dist-info/METADATA
pyburg_pkg_peresan-1.4.1.dist-info/WHEEL
pyburg_pkg_peresan-1.4.1.dist-info/top_level.txt
pyburg_pkg_peresan-1.4.1.dist-info/RECORD
