Metadata-Version: 2.1
Name: pyburg-pkg-peresan
Version: 1.4.1
Summary: A BURG (Bottom-Up Rewrite Grammar) instruction selection compiler generator
Home-page: https://github.com/pedroreissantos/pyburg
Author: Pedro Reis dos Santos
Author-email: reis.santos@tecnico.ulisboa.pt
License: MIT
Classifier: Programming Language :: Python :: 3
Classifier: License :: OSI Approved :: MIT License
Classifier: Operating System :: OS Independent
Classifier: Intended Audience :: Developers
Classifier: Topic :: Software Development :: Compilers
Classifier: Development Status :: 3 - Alpha
Classifier: Environment :: Console
Requires-Python: >=3.6
License-File: LICENSE
Requires-Dist: ply
